[
  {
    "number": "1",
    "url": "https://s.weibo.com/weibo?q=%23%E9%BE%99%E4%B8%B9%E5%A6%AE%E6%94%B6%E5%88%B0%E6%8A%A5%E5%A4%87%E4%BA%86%E5%90%97%23&Refer=top",
    "topic": "龙丹妮收到报备了吗",
    "popularity": "3932998"
  },
  {
    "number": "2",
    "url": "https://s.weibo.com/weibo?q=%23%E6%B1%9F%E8%8B%8F%E5%A4%A7%E5%AD%A6%E9%80%9A%E6%8A%A5%E5%AD%A6%E7%94%9F%E5%9D%A0%E6%A5%BC%E8%BA%AB%E4%BA%A1%E4%BA%8B%E4%BB%B6%23&Refer=top",
    "topic": "江苏大学通报学生坠楼身亡事件",
    "popularity": "2736242"
  },
  {
    "number": "3",
    "url": "https://s.weibo.com/weibo?q=%23%E8%A1%8C%E8%B5%B0%E7%9A%84%E9%81%BF%E9%9B%B7%E9%92%88%23&topic_ad=1&Refer=top",
    "topic": "行走的避雷针",
    "popularity": "2666455"
  },
  {
    "number": "4",
    "url": "https://s.weibo.com/weibo?q=%E5%A4%8F%E4%B9%8B%E5%85%89%E6%81%8B%E6%83%85&Refer=top",
    "topic": "夏之光恋情",
    "popularity": "2495596"
  },
  {
    "number": "5",
    "url": "https://s.weibo.com/weibo?q=%23%E5%A4%8D%E6%96%B9%E6%9D%BF%E8%93%9D%E6%A0%B9%E5%AF%B9%E6%96%B0%E5%86%A0%E7%97%85%E6%AF%92%E6%9C%89%E6%95%88%23&Refer=top",
    "topic": "复方板蓝根对新冠病毒有效",
    "popularity": "2219047"
  },
  {
    "number": "6",
    "url": "https://s.weibo.com/weibo?q=%23%E5%86%8D%E5%BF%99%E4%B9%9F%E8%A6%81%E5%A5%BD%E5%A5%BD%E5%90%83%E9%A5%AD%23&Refer=top",
    "topic": "再忙也要好好吃饭",
    "popularity": "1703199"
  },
  {
    "number": "7",
    "url": "https://s.weibo.com/weibo?q=%23%E4%BB%BB%E8%B1%AA%E9%81%93%E6%AD%89%23&Refer=top",
    "topic": "任豪道歉",
    "popularity": "1612167"
  },
  {
    "number": "8",
    "url": "https://s.weibo.com/weibo?q=%E5%B9%BF%E5%B7%9E%E7%96%AB%E6%83%85&Refer=top",
    "topic": "广州疫情",
    "popularity": "1576095"
  },
  {
    "number": "9",
    "url": "https://s.weibo.com/weibo?q=%23%E9%9D%92%E5%B2%9B%E6%AD%A4%E6%AC%A1%E7%96%AB%E6%83%85%E4%B8%BA%E5%8C%BB%E9%99%A2%E8%81%9A%E9%9B%86%E6%80%A7%E7%96%AB%E6%83%85%23&Refer=top",
    "topic": "青岛此次疫情为医院聚集性疫情",
    "popularity": "1420603"
  },
  {
    "number": "10",
    "url": "https://s.weibo.com/weibo?q=%23%E5%85%A8%E6%97%A5%E7%A9%BA%E5%AE%A3%E5%B8%83%E9%99%8D%E8%96%AA%E5%B9%B6%E5%85%81%E8%AE%B8%E5%91%98%E5%B7%A5%E6%90%9E%E5%89%AF%E4%B8%9A%23&Refer=top",
    "topic": "全日空宣布降薪并允许员工搞副业",
    "popularity": "1224938"
  },
  {
    "number": "11",
    "url": "https://s.weibo.com/weibo?q=%E5%96%9C%E5%AE%9D&Refer=top",
    "topic": "喜宝",
    "popularity": "1223569"
  },
  {
    "number": "12",
    "url": "https://s.weibo.com/weibo?q=%23%E4%B8%8A%E6%B5%B7%E7%A0%B4%E8%8E%B7%E9%A6%96%E4%BE%8B%E7%BD%91%E7%BA%A2%E7%9B%B4%E6%92%AD%E5%B8%A6%E8%B4%A7%E5%94%AE%E5%81%87%E6%A1%88%23&Refer=top",
    "topic": "上海破获首例网红直播带货售假案",
    "popularity": "1094446"
  },
  {
    "number": "13",
    "url": "https://s.weibo.com/weibo?q=%23S10%E9%97%A8%E7%A5%A8%E6%91%87%E5%8F%B7%E7%BB%93%E6%9E%9C%23&Refer=top",
    "topic": "S10门票摇号结果",
    "popularity": "881957"
  },
  {
    "number": "14",
    "url": "https://s.weibo.com/weibo?q=%23%E5%BC%A0%E5%9F%B9%E8%90%8C%E5%A6%BB%E5%AD%90%E7%A7%B0%E5%8F%AA%E6%83%B3%E8%A6%81%E5%A5%B3%E5%84%BF%E6%8A%9A%E5%85%BB%E6%9D%83%23&Refer=top",
    "topic": "张培萌妻子称只想要女儿抚养权",
    "popularity": "762955"
  },
  {
    "number": "15",
    "url": "https://s.weibo.com/weibo?q=%23%E6%88%90%E9%83%BD%E5%A4%A7%E5%AD%A6%E5%85%9A%E5%A7%94%E4%B9%A6%E8%AE%B0%E6%AF%9B%E6%B4%AA%E6%B6%9B%E7%9A%84%E9%81%97%E4%BD%93%E5%B7%B2%E8%A2%AB%E6%89%BE%E5%88%B0%23&Refer=top",
    "topic": "成都大学党委书记毛洪涛的遗体已被找到",
    "popularity": "651619"
  },
  {
    "number": "16",
    "url": "https://s.weibo.com/weibo?q=%E8%8A%B1%E9%83%BD&Refer=top",
    "topic": "花都",
    "popularity": "646517"
  },
  {
    "number": "17",
    "url": "https://s.weibo.com/weibo?q=%E9%92%9F%E4%B8%BD%E4%B8%BD&Refer=top",
    "topic": "钟丽丽",
    "popularity": "636394"
  },
  {
    "number": "18",
    "url": "https://s.weibo.com/weibo?q=%E6%9D%A8%E5%B8%85&Refer=top",
    "topic": "杨帅",
    "popularity": "629962"
  },
  {
    "number": "19",
    "url": "https://s.weibo.com/weibo?q=%23%E8%80%81%E5%B8%88%E5%B0%86%E4%B8%80%E6%AC%A1%E6%80%A7%E9%A4%90%E7%9B%92%E6%94%B9%E9%80%A0%E6%88%90%E6%98%99%E8%8A%B1%E7%81%AF%23&Refer=top",
    "topic": "老师将一次性餐盒改造成昙花灯",
    "popularity": "625175"
  },
  {
    "number": "20",
    "url": "https://s.weibo.com/weibo?q=%23%E4%B8%AD%E5%9B%BD%E7%AC%AC%E4%B8%80%E9%A2%97%E5%8E%9F%E5%AD%90%E5%BC%B9%E8%AF%95%E7%88%86%E7%9C%9F%E5%AE%9E%E5%BD%B1%E5%83%8F%23&Refer=top",
    "topic": "中国第一颗原子弹试爆真实影像",
    "popularity": "618950"
  },
  {
    "number": "21",
    "url": "https://s.weibo.com/weibo?q=%23%E5%8D%97%E6%96%B9%E8%8F%9C%E5%B8%82%E5%9C%BA%E6%9C%89%E5%A4%9A%E8%B4%B4%E5%BF%83%23&Refer=top",
    "topic": "南方菜市场有多贴心",
    "popularity": "611829"
  },
  {
    "number": "22",
    "url": "https://s.weibo.com/weibo?q=%23%E5%AD%99%E7%87%95%E5%A7%BF%E4%B8%BA%E5%AD%9F%E7%BE%8E%E5%B2%90%E5%BA%86%E7%94%9F%E6%96%87%E6%A1%88%23&Refer=top",
    "topic": "孙燕姿为孟美岐庆生文案",
    "popularity": "601373"
  },
  {
    "number": "23",
    "url": "https://s.weibo.com/weibo?q=%23%E6%89%93%E5%B7%A5%E4%BA%BA%E4%BD%A0%E5%A5%BD%E7%8B%A0%E7%9A%84%E5%BF%83%23&Refer=top",
    "topic": "打工人你好狠的心",
    "popularity": "596707"
  },
  {
    "number": "24",
    "url": "https://s.weibo.com/weibo?q=%23%E9%9D%92%E5%B2%9B%E6%A0%B8%E9%85%B8%E6%A3%80%E6%B5%8B%E4%B8%80%E5%B9%95%E8%8E%B7%E7%BD%91%E5%8F%8B%E7%82%B9%E8%B5%9E%23&Refer=top",
    "topic": "青岛核酸检测一幕获网友点赞",
    "popularity": "450804"
  },
  {
    "number": "25",
    "url": "https://s.weibo.com/weibo?q=%23%E7%94%B5%E7%AB%9E%E7%8F%AD%E7%9A%84%E4%BD%9C%E4%B8%9A%23&Refer=top",
    "topic": "电竞班的作业",
    "popularity": "447743"
  },
  {
    "number": "26",
    "url": "https://s.weibo.com/weibo?q=%23%E5%85%A8%E7%90%83%E9%A6%96%E4%B8%AA%E5%9F%83%E5%8D%9A%E6%8B%89%E7%97%85%E6%AF%92%E6%B2%BB%E7%96%97%E6%96%B9%E6%B3%95%23&Refer=top",
    "topic": "全球首个埃博拉病毒治疗方法",
    "popularity": "441308"
  },
  {
    "number": "27",
    "url": "https://s.weibo.com/weibo?q=%E4%BB%BB%E8%B1%AA%E7%8E%8B%E8%80%85%E8%8D%A3%E8%80%80&Refer=top",
    "topic": "任豪王者荣耀",
    "popularity": "431868"
  },
  {
    "number": "28",
    "url": "https://s.weibo.com/weibo?q=%23%E6%9D%8E%E6%A0%8B%E6%97%AD%E8%BA%AB%E6%9D%90%23&Refer=top",
    "topic": "李栋旭身材",
    "popularity": "430704"
  },
  {
    "number": "29",
    "url": "https://s.weibo.com/weibo?q=%E8%8E%AB%E9%9B%B7%E8%BE%9E%E8%81%8C&Refer=top",
    "topic": "莫雷辞职",
    "popularity": "421493"
  },
  {
    "number": "30",
    "url": "https://s.weibo.com/weibo?q=%23%E6%B3%B0%E5%9B%BD%E7%88%86%E5%8F%91%E6%8A%97%E8%AE%AE%E7%A4%BA%E5%A8%81%E6%B4%BB%E5%8A%A8%23&Refer=top",
    "topic": "泰国爆发抗议示威活动",
    "popularity": "411631"
  },
  {
    "number": "31",
    "url": "https://s.weibo.com/weibo?q=%23%E5%90%8C%E6%B5%8E%E5%A4%A7%E5%AD%A6%E6%96%B0%E7%94%9F%E4%BD%9C%E4%B8%9A%E6%AF%8F%E4%BB%BD10%E7%B1%B3%E9%95%BF%23&Refer=top",
    "topic": "同济大学新生作业每份10米长",
    "popularity": "401575"
  },
  {
    "number": "32",
    "url": "https://s.weibo.com/weibo?q=%23%E9%87%91%E9%92%9F%E5%A4%A7%E5%B0%86%E5%85%A5%E4%BC%8D%23&Refer=top",
    "topic": "金钟大将入伍",
    "popularity": "389064"
  },
  {
    "number": "33",
    "url": "https://s.weibo.com/weibo?q=%23%E5%85%A8%E5%9B%BD%E7%BB%9F%E4%B8%80%E7%9A%84%E5%AE%B6%E5%BA%AD%E7%BE%A4%E5%90%8D%E7%A7%B0%23&Refer=top",
    "topic": "全国统一的家庭群名称",
    "popularity": "388192"
  },
  {
    "number": "34",
    "url": "https://s.weibo.com/weibo?q=%23%E5%9B%9B%E5%B7%9D%E4%B8%80%E4%B8%AD%E5%AD%A6%E8%80%81%E5%B8%88%E5%A4%B1%E8%81%946%E5%A4%A9%23&Refer=top",
    "topic": "四川一中学老师失联6天",
    "popularity": "375971"
  },
  {
    "number": "35",
    "url": "https://s.weibo.com/weibo?q=%23%E7%95%99%E5%AD%A6%E7%94%9F%E5%9B%BD%E5%A4%96%E8%A1%97%E5%A4%B4%E5%BC%B9%E5%8F%A4%E7%AD%9D%E6%83%8A%E8%89%B3%E5%A4%96%E5%9B%BD%E4%BA%BA%23&Refer=top",
    "topic": "留学生国外街头弹古筝惊艳外国人",
    "popularity": "303575"
  },
  {
    "number": "36",
    "url": "https://s.weibo.com/weibo?q=%E5%BA%9F%E6%96%87%E7%BD%91&Refer=top",
    "topic": "废文网",
    "popularity": "300796"
  },
  {
    "number": "37",
    "url": "https://s.weibo.com/weibo?q=%23%E6%80%8E%E6%A0%B7%E8%AE%A4%E8%AF%86%E8%87%AA%E5%B7%B1%E5%96%9C%E6%AC%A2%E7%9A%84%E5%A5%B3%E7%94%9F%23&Refer=top",
    "topic": "怎样认识自己喜欢的女生",
    "popularity": "286472"
  },
  {
    "number": "38",
    "url": "https://s.weibo.com/weibo?q=%23%E5%B0%8F%E4%BC%99%E8%A7%82%E4%BC%97%E5%B8%AD%E6%97%A0%E5%AE%9E%E7%89%A9%E6%89%93%E9%BC%93%23&Refer=top",
    "topic": "小伙观众席无实物打鼓",
    "popularity": "267332"
  },
  {
    "number": "39",
    "url": "https://s.weibo.com/weibo?q=%E4%B8%8A%E6%B5%B7%E5%9C%B0%E9%93%81&Refer=top",
    "topic": "上海地铁",
    "popularity": "263163"
  },
  {
    "number": "40",
    "url": "https://s.weibo.com/weibo?q=%E5%BB%BA%E8%A1%8C%E7%AC%94%E8%AF%95&Refer=top",
    "topic": "建行笔试",
    "popularity": "259734"
  },
  {
    "number": "41",
    "url": "https://s.weibo.com/weibo?q=%23%E5%A4%AE%E8%A7%86%E4%BD%93%E8%82%B2%E9%A2%91%E9%81%93%E5%8F%91%E8%A8%80%E4%BA%BA%E8%B0%88%E8%8E%AB%E9%9B%B7%E8%BE%9E%E8%81%8C%23&Refer=top",
    "topic": "央视体育频道发言人谈莫雷辞职",
    "popularity": "245462"
  },
  {
    "number": "42",
    "url": "https://s.weibo.com/weibo?q=%23%E5%85%A8%E7%90%83%E6%9C%896.9%E4%BA%BF%E4%BA%BA%E5%9C%A8%E6%8C%A8%E9%A5%BF%23&Refer=top",
    "topic": "全球有6.9亿人在挨饿",
    "popularity": "225541"
  },
  {
    "number": "43",
    "url": "https://s.weibo.com/weibo?q=%E6%9B%BC%E8%B0%B7&Refer=top",
    "topic": "曼谷",
    "popularity": "219322"
  },
  {
    "number": "44",
    "url": "https://s.weibo.com/weibo?q=%23%E4%B8%AD%E5%9B%BD%E9%A9%BB%E6%84%8F%E5%A4%A7%E5%88%A9%E4%BD%BF%E9%A6%86%E5%8F%91%E5%B8%83%E7%B4%A7%E6%80%A5%E6%8F%90%E7%A4%BA%23&Refer=top",
    "topic": "中国驻意大利使馆发布紧急提示",
    "popularity": "217470"
  },
  {
    "number": "45",
    "url": "https://s.weibo.com/weibo?q=%23%E5%94%90%E5%AB%A3%E5%A4%B4%E5%B7%BE%E9%80%A0%E5%9E%8B%23&Refer=top",
    "topic": "唐嫣头巾造型",
    "popularity": "202408"
  },
  {
    "number": "46",
    "url": "https://s.weibo.com/weibo?q=%E4%B9%9D%E5%B0%BE%E7%8B%90%E4%BC%A0&Refer=top",
    "topic": "九尾狐传",
    "popularity": "197720"
  },
  {
    "number": "47",
    "url": "https://s.weibo.com/weibo?q=%23%E8%8B%B9%E6%9E%9C%E5%9B%9E%E5%BA%94%E4%B8%8D%E9%85%8D%E8%80%B3%E6%9C%BA%E5%92%8C%E5%85%85%E7%94%B5%E5%99%A8%23&Refer=top",
    "topic": "苹果回应不配耳机和充电器",
    "popularity": "194632"
  },
  {
    "number": "48",
    "url": "https://s.weibo.com/weibo?q=%23%E9%BC%93%E5%8A%B1%E4%B8%AD%E5%B0%8F%E5%AD%A6%E6%AF%8F%E5%A4%A9%E5%BC%80%E8%AE%BE%E4%B8%80%E8%8A%82%E4%BD%93%E8%82%B2%E8%AF%BE%23&Refer=top",
    "topic": "鼓励中小学每天开设一节体育课",
    "popularity": "193786"
  },
  {
    "number": "49",
    "url": "https://s.weibo.com/weibo?q=%E6%AD%A6%E6%B1%89%E9%80%81%E8%8F%9C%E4%BA%BA%E8%8E%B7%E8%AF%84%E8%81%94%E5%90%88%E5%9B%BD%E7%B2%AE%E9%A3%9F%E8%8B%B1%E9%9B%84&Refer=top",
    "topic": "武汉送菜人获评联合国粮食英雄",
    "popularity": "185186"
  },
  {
    "number": "50",
    "url": "https://s.weibo.com/weibo?q=%E5%95%86%E5%AE%B6%E5%9B%9E%E5%BA%94%E7%94%A8%E7%BF%A0%E9%B8%9F%E7%BE%BD%E6%AF%9B%E5%88%B6%E9%A5%B0%E5%93%81&Refer=top",
    "topic": "商家回应用翠鸟羽毛制饰品",
    "popularity": "183150"
  }
]