[
  {
    "number": "1",
    "url": "https://s.weibo.com/weibo?q=%23%E7%A0%94%E7%A9%B6%E7%94%9F%E4%B9%9D%E7%82%B9%E4%B8%8D%E8%B5%B7%E5%BA%8A%E6%89%A35%E5%88%86%E8%A1%8C%E4%B8%BA%E5%88%86%23&Refer=top",
    "topic": "研究生九点不起床扣5分行为分",
    "popularity": "3938231"
  },
  {
    "number": "2",
    "url": "https://s.weibo.com/weibo?q=%23%E7%94%B7%E5%AD%90%E4%B8%BA%E5%90%93%E5%94%AC%E5%90%8C%E5%AD%A6%E5%B0%86%E6%A0%B8%E9%85%B8%E7%BB%93%E6%9E%9C%E6%94%B9%E6%88%90%E9%98%B3%E6%80%A7%23&Refer=top",
    "topic": "男子为吓唬同学将核酸结果改成阳性",
    "popularity": "2439059"
  },
  {
    "number": "3",
    "url": "https://s.weibo.com/weibo?q=%23%E7%A7%A6%E7%89%9Brap%E6%97%B6GAI%E7%9A%84%E8%A1%A8%E6%83%85%23&Refer=top",
    "topic": "秦牛rap时GAI的表情",
    "popularity": "2336785"
  },
  {
    "number": "4",
    "url": "https://s.weibo.com/weibo?q=%23%E9%87%91%E6%98%9F%E8%AF%B4%E8%B0%A2%E5%A8%9C%E4%B8%BB%E6%8C%81%E4%B8%A4%E4%B8%AA%E6%9E%81%E7%AB%AF%23&Refer=top",
    "topic": "金星说谢娜主持两个极端",
    "popularity": "2041845"
  },
  {
    "number": "5",
    "url": "https://s.weibo.com/weibo?q=%23%E5%93%87%E5%94%A7%E5%94%A7%E5%93%87%E5%8F%91%E6%96%87%23&Refer=top",
    "topic": "哇唧唧哇发文",
    "popularity": "1636064"
  },
  {
    "number": "6",
    "url": "https://s.weibo.com/weibo?q=%23%E7%BE%8E%E9%A3%9F%E7%9C%9F%E9%A6%99%E7%8E%B0%E5%9C%BA%23&Refer=top",
    "topic": "美食真香现场",
    "popularity": "1628621"
  },
  {
    "number": "7",
    "url": "https://s.weibo.com/weibo?q=%23%E6%88%90%E9%83%BD%E5%A4%A7%E5%AD%A6%E5%85%9A%E5%A7%94%E4%B9%A6%E8%AE%B0%E6%AF%9B%E6%B4%AA%E6%B6%9B%E7%9A%84%E9%81%97%E4%BD%93%E5%B7%B2%E8%A2%AB%E6%89%BE%E5%88%B0%23&Refer=top",
    "topic": "成都大学党委书记毛洪涛的遗体已被找到",
    "popularity": "891759"
  },
  {
    "number": "8",
    "url": "https://s.weibo.com/weibo?q=%23%E8%8B%B9%E6%9E%9C%E5%9B%9E%E5%BA%94%E4%B8%8D%E9%85%8D%E8%80%B3%E6%9C%BA%E5%92%8C%E5%85%85%E7%94%B5%E5%99%A8%23&Refer=top",
    "topic": "苹果回应不配耳机和充电器",
    "popularity": "833863"
  },
  {
    "number": "9",
    "url": "https://s.weibo.com/weibo?q=%E8%8B%B1%E5%A5%B3%E7%8E%8B%E6%97%B6%E9%9A%947%E4%B8%AA%E6%9C%88%E5%90%8E%E9%A6%96%E6%AC%A1%E5%8F%82%E5%8A%A0%E5%85%AC%E5%BC%80%E6%B4%BB%E5%8A%A8&Refer=top",
    "topic": "英女王时隔7个月后首次参加公开活动",
    "popularity": "789740"
  },
  {
    "number": "10",
    "url": "https://s.weibo.com/weibo?q=%23%E5%B9%BF%E5%B7%9E%E6%97%A0%E7%97%87%E7%8A%B6%E6%84%9F%E6%9F%93%E8%80%85%E5%8F%91%E5%A3%B0%23&Refer=top",
    "topic": "广州无症状感染者发声",
    "popularity": "754621"
  },
  {
    "number": "11",
    "url": "https://s.weibo.com/weibo?q=%23%E5%86%AF%E7%BB%8D%E5%B3%B0%E7%BB%99%E8%B5%B5%E4%B8%BD%E9%A2%96%E7%9A%84%E7%A5%9D%E7%A6%8F%E8%AF%84%E8%AE%BA%E8%A2%AB%E6%B7%B9%E4%BA%86%23&Refer=top",
    "topic": "冯绍峰给赵丽颖的祝福评论被淹了",
    "popularity": "602377"
  },
  {
    "number": "12",
    "url": "https://s.weibo.com/weibo?q=%23%E5%A4%8D%E6%96%B9%E6%9D%BF%E8%93%9D%E6%A0%B9%E5%AF%B9%E6%96%B0%E5%86%A0%E7%97%85%E6%AF%92%E6%9C%89%E6%95%88%23&Refer=top",
    "topic": "复方板蓝根对新冠病毒有效",
    "popularity": "430840"
  },
  {
    "number": "13",
    "url": "https://s.weibo.com/weibo?q=%23%E4%B8%AD%E8%80%83%E4%BD%93%E8%82%B2%E5%B0%86%E8%BE%BE%E5%88%B0%E5%92%8C%E8%AF%AD%E6%95%B0%E5%A4%96%E5%90%8C%E5%88%86%E5%80%BC%E6%B0%B4%E5%B9%B3%23&Refer=top",
    "topic": "中考体育将达到和语数外同分值水平",
    "popularity": "411506"
  },
  {
    "number": "14",
    "url": "https://s.weibo.com/weibo?q=%234%E4%BA%BA26%E5%A4%A9%E6%8D%95%E9%B8%9F8%E4%B8%87%E4%BD%99%E5%8F%AA%23&Refer=top",
    "topic": "4人26天捕鸟8万余只",
    "popularity": "316001"
  },
  {
    "number": "15",
    "url": "https://s.weibo.com/weibo?q=%E5%8D%97%E8%88%AA%E5%9B%9E%E5%BA%94%E4%B9%98%E5%AE%A2%E6%8A%A0%E5%87%BA%E6%B0%A7%E6%B0%94%E9%9D%A2%E7%BD%A9%E8%87%B4%E5%BB%B6%E8%AF%AF&Refer=top",
    "topic": "南航回应乘客抠出氧气面罩致延误",
    "popularity": "301221"
  },
  {
    "number": "16",
    "url": "https://s.weibo.com/weibo?q=%23%E6%95%99%E8%82%B2%E9%83%A8%E8%B0%88%E4%BD%93%E8%82%B2%E8%80%81%E5%B8%88%E5%BD%93%E7%8F%AD%E4%B8%BB%E4%BB%BB%E9%81%AD%E6%8A%95%E8%AF%89%23&Refer=top",
    "topic": "教育部谈体育老师当班主任遭投诉",
    "popularity": "298617"
  },
  {
    "number": "17",
    "url": "https://s.weibo.com/weibo?q=%23%E5%92%8C%E5%AF%B9%E8%B1%A1%E6%8E%A5%E5%90%BB%E5%90%8E%E6%93%A6%E5%98%B4%23&Refer=top",
    "topic": "和对象接吻后擦嘴",
    "popularity": "298503"
  },
  {
    "number": "18",
    "url": "https://s.weibo.com/weibo?q=%23%E6%96%B0%E5%8C%85%E8%A3%85iPhone11%E4%B9%9F%E4%B8%8D%E9%80%81%E8%80%B3%E6%9C%BA%E5%85%85%E7%94%B5%E5%99%A8%23&Refer=top",
    "topic": "新包装iPhone11也不送耳机充电器",
    "popularity": "298307"
  },
  {
    "number": "19",
    "url": "https://s.weibo.com/weibo?q=%2318%E5%B2%81%E5%A5%B3%E5%A4%A7%E5%AD%A6%E7%94%9F%E6%8D%90%E7%8C%AE%E9%81%97%E4%BD%93%23&Refer=top",
    "topic": "18岁女大学生捐献遗体",
    "popularity": "297826"
  },
  {
    "number": "20",
    "url": "https://s.weibo.com/weibo?q=%E5%BE%90%E6%98%8E%E6%98%9F&Refer=top",
    "topic": "徐明星",
    "popularity": "297495"
  },
  {
    "number": "21",
    "url": "https://s.weibo.com/weibo?q=%23%E6%9D%A8%E8%BF%AA%E4%B8%B4%E5%9C%BA%E5%8F%8D%E5%BA%94%E6%9C%89%E5%A4%9A%E5%BC%BA%23&Refer=top",
    "topic": "杨迪临场反应有多强",
    "popularity": "297386"
  },
  {
    "number": "22",
    "url": "https://s.weibo.com/weibo?q=%23%E5%B0%8F%E7%B1%B3%E9%95%BF%E8%99%B9%E7%AD%89%E8%A2%AB%E6%96%B0%E5%8D%8E%E7%A4%BE%E7%82%B9%E5%90%8D%23&Refer=top",
    "topic": "小米长虹等被新华社点名",
    "popularity": "297109"
  },
  {
    "number": "23",
    "url": "https://s.weibo.com/weibo?q=%E7%81%AB%E6%98%9F%E6%83%85%E6%8A%A5%E5%B1%80&Refer=top",
    "topic": "火星情报局",
    "popularity": "296761"
  },
  {
    "number": "24",
    "url": "https://s.weibo.com/weibo?q=%23%E8%B5%B5%E7%AB%8B%E5%9D%9A%E6%89%B9%E8%93%AC%E4%BD%A9%E5%A5%A5%E7%9D%81%E7%9D%80%E7%9C%BC%E7%9D%9B%E8%AF%B4%E7%9E%8E%E8%AF%9D%23&Refer=top",
    "topic": "赵立坚批蓬佩奥睁着眼睛说瞎话",
    "popularity": "296473"
  },
  {
    "number": "25",
    "url": "https://s.weibo.com/weibo?q=%23%E9%9D%92%E5%B2%9B72%E5%B0%8F%E6%97%B6%23&Refer=top",
    "topic": "青岛72小时",
    "popularity": "296096"
  },
  {
    "number": "26",
    "url": "https://s.weibo.com/weibo?q=%23%E5%A4%8F%E4%B9%8B%E5%85%89%E5%90%91%E7%B2%89%E4%B8%9D%E9%9E%A0%E8%BA%AC%23&Refer=top",
    "topic": "夏之光向粉丝鞠躬",
    "popularity": "295888"
  },
  {
    "number": "27",
    "url": "https://s.weibo.com/weibo?q=%23%E6%9C%B4%E6%9C%89%E5%A4%A9%E6%88%96%E5%9B%A0%E6%8B%96%E6%AC%A0%E8%B5%94%E5%81%BF%E9%87%91%E8%A2%AB%E8%B5%B7%E8%AF%89%23&Refer=top",
    "topic": "朴有天或因拖欠赔偿金被起诉",
    "popularity": "295591"
  },
  {
    "number": "28",
    "url": "https://s.weibo.com/weibo?q=%23%E6%95%99%E8%82%B2%E9%83%A8%E5%9B%9E%E5%BA%94%E4%BD%93%E8%82%B2%E8%80%81%E5%B8%88%E5%BD%93%E7%8F%AD%E4%B8%BB%E4%BB%BB%E8%A2%AB%E6%8A%95%E8%AF%89%23&Refer=top",
    "topic": "教育部回应体育老师当班主任被投诉",
    "popularity": "295503"
  },
  {
    "number": "29",
    "url": "https://s.weibo.com/weibo?q=%23%E4%B9%A1%E6%9D%91%E5%8C%BB%E7%94%9F%E9%81%97%E6%84%BF%E7%A9%BF%E6%88%B4%E6%95%B4%E9%BD%90%E6%8D%90%E7%BB%99%E5%9B%BD%E5%AE%B6%23&Refer=top",
    "topic": "乡村医生遗愿穿戴整齐捐给国家",
    "popularity": "295341"
  },
  {
    "number": "30",
    "url": "https://s.weibo.com/weibo?q=SN%20JDG&Refer=top",
    "topic": "SN JDG",
    "popularity": "295340"
  },
  {
    "number": "31",
    "url": "https://s.weibo.com/weibo?q=%23%E5%94%90%E8%89%BA%E6%98%95%E9%A6%96%E6%94%AFvlog%23&Refer=top",
    "topic": "唐艺昕首支vlog",
    "popularity": "295098"
  },
  {
    "number": "32",
    "url": "https://s.weibo.com/weibo?q=%23%E6%9D%8E%E7%8E%B0%E8%A5%BF%E8%A3%85%E7%94%9F%E5%9B%BE%23&Refer=top",
    "topic": "李现西装生图",
    "popularity": "289925"
  },
  {
    "number": "33",
    "url": "https://s.weibo.com/weibo?q=%23%E8%A2%AB%E5%89%A7%E5%B8%A6%E7%81%AB%E7%9A%84%E5%8F%96%E6%99%AF%E5%9C%B0%23&Refer=top",
    "topic": "被剧带火的取景地",
    "popularity": "275086"
  },
  {
    "number": "34",
    "url": "https://s.weibo.com/weibo?q=%23%E5%8D%97%E9%83%A8%E6%88%98%E5%8C%BA%E7%A9%BA%E5%86%9B%E8%B6%85%E4%BD%8E%E7%A9%BA%E9%A3%9E%E8%A1%8C%E8%AE%AD%E7%BB%83%23&Refer=top",
    "topic": "南部战区空军超低空飞行训练",
    "popularity": "261487"
  },
  {
    "number": "35",
    "url": "https://s.weibo.com/weibo?q=%23%E5%86%9B%E8%AE%AD%E4%B8%8B%E9%9B%A8%E6%97%B6%E8%A2%9C%E5%AD%90%E6%B2%A1%E6%B4%97%E5%B9%B2%E5%87%80%23&Refer=top",
    "topic": "军训下雨时袜子没洗干净",
    "popularity": "242850"
  },
  {
    "number": "36",
    "url": "https://s.weibo.com/weibo?q=%E6%B2%88%E9%92%B2%E5%8D%9A&Refer=top",
    "topic": "沈钲博",
    "popularity": "233653"
  },
  {
    "number": "37",
    "url": "https://s.weibo.com/weibo?q=%23%E9%BB%84%E6%98%8E%E6%98%8A%E5%9B%9E%E5%BA%94%E6%96%B0%E6%AD%8C%E6%B5%B7%E6%8A%A5%E4%BA%89%E8%AE%AE%23&Refer=top",
    "topic": "黄明昊回应新歌海报争议",
    "popularity": "233494"
  },
  {
    "number": "38",
    "url": "https://s.weibo.com/weibo?q=%23%E6%B3%B0%E5%9B%BD%E6%8B%9F%E5%90%91%E4%B8%AD%E5%9B%BD%E6%B8%B8%E5%AE%A2%E5%BC%80%E6%94%BE%23&Refer=top",
    "topic": "泰国拟向中国游客开放",
    "popularity": "217574"
  },
  {
    "number": "39",
    "url": "https://s.weibo.com/weibo?q=%E5%B9%BF%E5%B7%9E%E7%96%AB%E6%83%85&Refer=top",
    "topic": "广州疫情",
    "popularity": "211757"
  },
  {
    "number": "40",
    "url": "https://s.weibo.com/weibo?q=%E8%8B%B1%E9%9B%84%E8%81%94%E7%9B%9F%E6%8E%92%E4%BD%8D&Refer=top",
    "topic": "英雄联盟排位",
    "popularity": "206342"
  },
  {
    "number": "41",
    "url": "https://s.weibo.com/weibo?q=%23%E9%B9%BF%E6%99%97%E9%87%8D%E5%BA%86%23&Refer=top",
    "topic": "鹿晗重庆",
    "popularity": "204206"
  },
  {
    "number": "42",
    "url": "https://s.weibo.com/weibo?q=R1SE%E6%96%B0%E4%B8%93%E9%A2%84%E5%94%AE%E5%8F%8A%E7%AD%BE%E5%94%AE%E4%BC%9A%E6%8E%A8%E8%BF%9F&Refer=top",
    "topic": "R1SE新专预售及签售会推迟",
    "popularity": "201704"
  },
  {
    "number": "43",
    "url": "https://s.weibo.com/weibo?q=%23%E4%B8%89%E5%8F%A5%E8%AF%9D%E8%AF%BB%E6%87%82%E5%BE%B7%E4%BA%91%E7%94%B7%E5%9B%A2%23&Refer=top",
    "topic": "三句话读懂德云男团",
    "popularity": "200411"
  },
  {
    "number": "44",
    "url": "https://s.weibo.com/weibo?q=%23%E6%88%98%E6%9C%BA%E9%81%AD%E9%B8%9F%E6%92%9E%E5%87%BB%E9%A3%9E%E8%A1%8C%E5%91%98%E8%A7%84%E9%81%BF%E5%B1%85%E6%B0%91%E5%8C%BA%E5%90%8E%E8%B7%B3%E4%BC%9E%23&Refer=top",
    "topic": "战机遭鸟撞击飞行员规避居民区后跳伞",
    "popularity": "196276"
  },
  {
    "number": "45",
    "url": "https://s.weibo.com/weibo?q=%23%E6%97%85%E8%A1%8C%E5%89%8D%E4%B8%80%E5%A4%A9%E7%9A%84%E6%88%91%23&Refer=top",
    "topic": "旅行前一天的我",
    "popularity": "194284"
  },
  {
    "number": "46",
    "url": "https://s.weibo.com/weibo?q=%23%E9%9F%A9%E5%9B%BD%E8%9C%82%E7%AA%9D%E7%85%A4%E4%BB%B7%E6%A0%BC%E6%9A%B4%E6%B6%A8%23&Refer=top",
    "topic": "韩国蜂窝煤价格暴涨",
    "popularity": "191038"
  },
  {
    "number": "47",
    "url": "https://s.weibo.com/weibo?q=%23%E4%B8%9C%E5%8C%97%E4%BA%BA%E5%B1%AF%E8%8F%9C%E6%9C%89%E5%A4%9A%E5%A4%B8%E5%BC%A0%23&Refer=top",
    "topic": "东北人屯菜有多夸张",
    "popularity": "189103"
  },
  {
    "number": "48",
    "url": "https://s.weibo.com/weibo?q=%E7%8E%8B%E6%B8%85%E8%BF%9C&Refer=top",
    "topic": "王清远",
    "popularity": "186821"
  },
  {
    "number": "49",
    "url": "https://s.weibo.com/weibo?q=%23%E6%9E%9C%E7%84%B6%E5%BF%AB%E4%B9%90%E5%BB%BA%E7%AB%8B%E5%9C%A8%E5%88%AB%E4%BA%BA%E7%97%9B%E8%8B%A6%E4%B8%8A%23&Refer=top",
    "topic": "果然快乐建立在别人痛苦上",
    "popularity": "179361"
  },
  {
    "number": "50",
    "url": "https://s.weibo.com/weibo?q=%E8%8A%B1%E9%83%BD&Refer=top",
    "topic": "花都",
    "popularity": "178901"
  }
]